websauna.magiclogin-1.0a2-py3.5-nspkg.pth
websauna/magiclogin/__init__.py
websauna/magiclogin/demo.py
websauna/magiclogin/login.py
websauna/magiclogin/models.py
websauna/magiclogin/requirelogin.py
websauna/magiclogin/views.py
websauna/magiclogin/conf/development-secrets.ini
websauna/magiclogin/conf/development.ini
websauna/magiclogin/conf/test.ini
websauna/magiclogin/demotemplates/requirelogin-example.html
websauna/magiclogin/demotemplates/site/nav.html
websauna/magiclogin/static/g_logo.svg
websauna/magiclogin/static/logo.png
websauna/magiclogin/static/magiclogin.css
websauna/magiclogin/templates/magiclogin/login.html
websauna/magiclogin/templates/magiclogin/login_email.html
websauna/magiclogin/templates/magiclogin/login_email_sent.html
websauna/magiclogin/templates/magiclogin/login_panel.html
websauna/magiclogin/templates/magiclogin/login_to_continue.html
websauna/magiclogin/templates/magiclogin/email/verify_email.body.html
websauna/magiclogin/templates/magiclogin/email/verify_email.body.txt
websauna/magiclogin/templates/magiclogin/email/verify_email.subject.txt
websauna/magiclogin/templates/social/facebook/login_snippet.html
websauna/magiclogin/templates/social/google/login_snippet.html
websauna/magiclogin/templates/social/twitter/login_snippet.html
websauna/magiclogin/tests/__init__.py
websauna/magiclogin/tests/conftest.py
websauna/magiclogin/tests/requireloginexamples.py
websauna/magiclogin/tests/test_email_login.py
websauna/magiclogin/tests/test_require_login.py
websauna/magiclogin/tests/utils.py
websauna.magiclogin-1.0a2.dist-info/DESCRIPTION.rst
websauna.magiclogin-1.0a2.dist-info/METADATA
websauna.magiclogin-1.0a2.dist-info/RECORD
websauna.magiclogin-1.0a2.dist-info/WHEEL
websauna.magiclogin-1.0a2.dist-info/entry_points.txt
websauna.magiclogin-1.0a2.dist-info/metadata.json
websauna.magiclogin-1.0a2.dist-info/namespace_packages.txt
websauna.magiclogin-1.0a2.dist-info/top_level.txt
